xia_module_terraform_gcs/__init__.py
xia_module_terraform_gcs/application_backend_gcs.py
xia_module_terraform_gcs/application_gcs.py
xia_module_terraform_gcs/backend_gcs.py
xia_module_terraform_gcs/cosmos_backend_gcs.py
xia_module_terraform_gcs/foundation_backend_gcs.py
xia_module_terraform_gcs/foundation_gcs.py
xia_module_terraform_gcs/templates/module-application-backend-gcs/base/main.tf
xia_module_terraform_gcs/templates/module-application-backend-gcs/cicd/github/workflow.yml
xia_module_terraform_gcs/templates/module-application-backend-gcs/config/core/tfstate.yaml
xia_module_terraform_gcs/templates/module-application-backend-gcs/module/main.tf
xia_module_terraform_gcs/templates/module-application-backend-gcs/module/variables.tf
xia_module_terraform_gcs/templates/module-application-state-gcs/activate/main.tf
xia_module_terraform_gcs/templates/module-application-state-gcs/activate/variables.tf
xia_module_terraform_gcs/templates/module-application-state-gcs/base/activate.tf
xia_module_terraform_gcs/templates/module-application-state-gcs/base/main.tf
xia_module_terraform_gcs/templates/module-application-state-gcs/cicd/github/workflow.yml
xia_module_terraform_gcs/templates/module-application-state-gcs/config/core/tfstate.yaml
xia_module_terraform_gcs/templates/module-application-state-gcs/module/main.tf
xia_module_terraform_gcs/templates/module-application-state-gcs/module/variables.tf
xia_module_terraform_gcs/templates/module-cosmos-backend-gcs/base/main.tf
xia_module_terraform_gcs/templates/module-cosmos-backend-gcs/cicd/github/workflow.yml
xia_module_terraform_gcs/templates/module-cosmos-backend-gcs/config/core/tfstate.yaml
xia_module_terraform_gcs/templates/module-cosmos-backend-gcs/module/main.tf
xia_module_terraform_gcs/templates/module-cosmos-backend-gcs/module/variables.tf
xia_module_terraform_gcs/templates/module-foundation-backend-gcs/base/main.tf
xia_module_terraform_gcs/templates/module-foundation-backend-gcs/cicd/github/workflow.yml
xia_module_terraform_gcs-0.0.26.dist-info/LICENSE
xia_module_terraform_gcs-0.0.26.dist-info/METADATA
xia_module_terraform_gcs-0.0.26.dist-info/WHEEL
xia_module_terraform_gcs-0.0.26.dist-info/top_level.txt
xia_module_terraform_gcs-0.0.26.dist-info/RECORD
