Metadata-Version: 2.1
Name: xia-module-terraform-gcs
Version: 0.0.26
Requires-Python: >=3.9
License-File: LICENSE
Requires-Dist: PyYAML
Requires-Dist: xia-module
